aeimputer/__init__.py
aeimputer/ae.py
aeimputer/early_stopper.py
aeimputer/imputer.py
aeimputer/utils.py
aeimputer/vae.py
ae_imputer-0.0.1.post2.dist-info/LICENSE
ae_imputer-0.0.1.post2.dist-info/METADATA
ae_imputer-0.0.1.post2.dist-info/WHEEL
ae_imputer-0.0.1.post2.dist-info/top_level.txt
ae_imputer-0.0.1.post2.dist-info/RECORD
