Metadata-Version: 2.1
Name: ae-imputer
Version: 0.0.1.post2
Summary: a python package used for missing data imputation via autoencoders
Home-page: https://github.com/stonegor/ae-imputer
Author: stonegor
Author-email: sstonegor@gmail.com
License: MIT
Classifier: License :: OSI Approved :: MIT License
Classifier: Programming Language :: Python :: 3.10
Classifier: Operating System :: OS Independent
Requires-Python: >=3.8.0
License-File: LICENSE
Requires-Dist: scikit-learn >=0.22
Requires-Dist: numpy >=1.20.0
Requires-Dist: pandas
Requires-Dist: torch
Provides-Extra: dev
Requires-Dist: twine >=4.0.2 ; extra == 'dev'
